poetry_demo_ks/__init__.py
poetry_demo_ks-0.1.0.dist-info/METADATA
poetry_demo_ks-0.1.0.dist-info/WHEEL
poetry_demo_ks-0.1.0.dist-info/RECORD
