Metadata-Version: 2.1
Name: poetry-demo-ks
Version: 0.1.0
Summary: 
Author: Kasra Safari
Author-email: kasrasafari@gmail.com
Requires-Python: >=3.9,<4.0
Classifier: Programming Language :: Python :: 3
Classifier: Programming Language :: Python :: 3.9
Classifier: Programming Language :: Python :: 3.10
Classifier: Programming Language :: Python :: 3.11
Requires-Dist: pendulum (>=2.1,<3.0)
